jamfAuth/__init__.py
support/__init__.py
support/configCheck.py
support/getToken.py
jamfAuth-0.3.4.dist-info/LICENSE
jamfAuth-0.3.4.dist-info/METADATA
jamfAuth-0.3.4.dist-info/WHEEL
jamfAuth-0.3.4.dist-info/top_level.txt
jamfAuth-0.3.4.dist-info/RECORD
