Metadata-Version: 2.1
Name: jamfAuth
Version: 0.3.4
Summary: A python script to authenticate with the Jamf Pro API.
Home-page: https://github.com/therealmacjeezy/JamfAuth
Author: Josh Harvey
Author-email: josh.harvey@jamf.com
Classifier: Development Status :: 5 - Production/Stable
Classifier: Operating System :: MacOS
Classifier: Programming Language :: Python :: 3
Classifier: Natural Language :: English
Requires-Python: >=3.8
License-File: LICENSE
Requires-Dist: requests (>=2.22.0)
Requires-Dist: keyring (>=18.0.1)
Requires-Dist: keyrings.alt ; platform_system == "Linux"
